close_useless_window_interval/__init__.py
close_useless_window_interval/main.py
close_useless_window_interval-0.1.9.dist-info/METADATA
close_useless_window_interval-0.1.9.dist-info/WHEEL
close_useless_window_interval-0.1.9.dist-info/RECORD
